MANIFEST.in
README.txt
setup.cfg
setup.py
XStatic_browser_update.egg-info/PKG-INFO
XStatic_browser_update.egg-info/SOURCES.txt
XStatic_browser_update.egg-info/dependency_links.txt
XStatic_browser_update.egg-info/namespace_packages.txt
XStatic_browser_update.egg-info/not-zip-safe
XStatic_browser_update.egg-info/requires.txt
XStatic_browser_update.egg-info/top_level.txt
xstatic/__init__.py
xstatic/pkg/__init__.py
xstatic/pkg/browser_update/__init__.py
xstatic/pkg/browser_update/data/update.js