Metadata-Version: 1.0
Name: XStatic-browser-update
Version: 1.0.1
Summary: browser-update 1.0 (XStatic packaging standard)
Home-page: UNKNOWN
Author: Nikunj Aggarwal
Author-email: nikunj2512@gmail.com
License: (same as browser-update)
Keywords: browser_update xstatic
Platform: any
